<?xml version="1.0" encoding="UTF-8"?><!--
This software and related documentation are proprietary to Siemens Product Lifecycle Management Software Inc.

(c) 2010 Siemens Product Lifecycle Management Software Inc. All Rights Reserved. 

All trademarks belong to their respective holders.
-->
<links topicSetID="spta_system" launchFile="index.html"><link parent="topicSet" id="spta_system" title="System modeling with external superelements" file="spta_system/id1298515.html"/><link parent="topicMap" id="id1298515" title="System modeling" file="spta_system/id1298522.html"/><link parent="topic" id="id1298522" title="System modeling with external superelements" file="spta_system/id1298522.html"/><link parent="topic" id="id1049828" title="Setup information" file="spta_system/id1298522.html#id1049828"/><link parent="topic" id="part_file_info" title="Locating the parts" file="spta_system/id275401.html"/><link parent="topic" id="role_for_course" title="NX Roles" file="spta_system/id275411.html"/><link parent="topic" id="system_prep" title="System preparation" file="spta_system/id306602.html"/><link parent="topic" id="id1267734" title="Using superelements in an assembly FEM" file="spta_system/id1267734.html"/><link parent="figure" id="genid_spta_system_9" title="Top: A system model. (1) The residual (nodes and elements). (2) Substructures (external superelements)." file="spta_system/id1267734.html#genid_spta_system_9"/><link parent="topic" id="id1290377" title="System modeling workflow" file="spta_system/id1290377.html"/><link parent="topic" id="id1290378" title="Generating external superelements for Advanced Simulation system models" file="spta_system/id1290378.html"/><link parent="topic" id="id1290379" title="Replacing a component FEM with a superelement" file="spta_system/id1290379.html"/><link parent="figure" id="genid_spta_system_18" title="A simple system model in the Simulation Navigator. (1) A component represented by the base FEM. (2) A component represented by a superelement." file="spta_system/id1290379.html#genid_spta_system_18"/><link parent="topic" id="id1346401" title="Superelement mapping considerations" file="spta_system/id1346401.html"/><link parent="topic" id="id1346402" title="Connecting superelement boundary nodes to the residual" file="spta_system/id1346402.html"/><link parent="figure" id="genid_spta_system_23" title="Two component FEMs connected using a geometry-based edge-face 1D connection." file="spta_system/id1346402.html#genid_spta_system_23"/><link parent="figure" id="genid_spta_system_24" title="The corresponding superelement boundary nodes inherit the edge-face connection in the system model." file="spta_system/id1346402.html#genid_spta_system_24"/><link parent="topic" id="id1290380" title="Superelement displays" file="spta_system/id1290380.html"/><link parent="figure" id="genid_spta_system_27" title="(1) An FE model representing a satellite payload. (2)The base FEM approximation of the superelement representation. (3) The same superelement displayed as a symbol. The boundary nodes are shown in red. (4) The boundary nodes displayed as unattached markers." file="spta_system/id1290380.html#genid_spta_system_27"/><link parent="topic" id="id1346404" title="Controlling the display of base FEM approximations" file="spta_system/id1346404.html"/><link parent="topic" id="id1290383" title="Supported system model solutions" file="spta_system/id1290383.html"/><link parent="topic" id="id1290381" title="Solving the system model" file="spta_system/id1290381.html"/><link parent="topic" id="id1346427" title="Example: Assigning external superelements in the bulk data file" file="spta_system/id1346427.html"/><link parent="topic" id="id1346428" title="Example: Defining superelement connections and orientation" file="spta_system/id1346428.html"/><link parent="topic" id="id1290382" title="Post-processing system models" file="spta_system/id1290382.html"/><link parent="figure" id="genid_spta_system_41" title="The Post-Processing Navigator. (1) The system model. (2) The system run solution. (3) The residual results subcase. (4) Superelement data blocks." file="spta_system/id1290382.html#genid_spta_system_41"/><link parent="topic" id="id1371724" title="Video: post-processing system models" file="spta_system/id1371724.html"/><link parent="topicMap" id="id1459467" title="Modeling with external superelements" file="spta_system/id1459469.html"/><link parent="topic" id="id1459469" title="Modeling with external superelements" file="spta_system/id1459469.html"/><link parent="topic" id="id1459473" title="Open the assembly FEM" file="spta_system/id1459473.html"/><link parent="topic" id="reset_dialog_box_settings" title="Reset the dialog box settings" file="spta_system/id412719.html"/><link parent="topic" id="id1459475" title="Create a new Simulation file" file="spta_system/id1459475.html"/><link parent="topic" id="id1459807" title="Define a modal solution" file="spta_system/id1459807.html"/><link parent="topic" id="id1459809" title="Review the simulation summary" file="spta_system/id1459809.html"/><link parent="topic" id="id1459821" title="Glue the end cap to the optical support" file="spta_system/id1459821.html"/><link parent="topic" id="id1459823" title="Solve the base_fem solution" file="spta_system/id1459823.html"/><link parent="topic" id="id1459825" title="Find the total degrees of freedom in the solution" file="spta_system/id1459825.html"/><link parent="topic" id="id1459847" title="Examine the results" file="spta_system/id1459847.html"/><link parent="topic" id="id1459849" title="Display the assembly FEM" file="spta_system/id1459849.html"/><link parent="topic" id="id1459896" title="Replace component FEMs with external superelements" file="spta_system/id1459896.html"/><link parent="topic" id="id1459898" title="Modify the superelement display" file="spta_system/id1459898.html"/><link parent="topic" id="id1459900" title="Display the simulation file" file="spta_system/id1459900.html"/><link parent="topic" id="id1459922" title="Clone the base_fem solution" file="spta_system/id1459922.html"/><link parent="topic" id="id1459924" title="Preview the solver input file" file="spta_system/id1459924.html"/><link parent="topic" id="id1461012" title="Review the simulation summary" file="spta_system/id1461012.html"/><link parent="topic" id="id1459941" title="Solve the system_run solution" file="spta_system/id1459941.html"/><link parent="topic" id="id1459943" title="Find the total degrees of freedom in the solution" file="spta_system/id1459943.html"/><link parent="topic" id="id1459945" title="Load external superelement results" file="spta_system/id1459945.html"/><link parent="topic" id="id1459977" title="Plot and overlay loaded superelement results" file="spta_system/id1459977.html"/><link parent="topic" id="id1459979" title="Scale deformations and hide element edges" file="spta_system/id1459979.html"/><link parent="topic" id="id1461051" title="Plot results from the base_fem solution" file="spta_system/id1461051.html"/><link parent="topic" id="id1461053" title="Edit the new post view" file="spta_system/id1461053.html"/><link parent="topic" id="id1460003" title="Examine additional modes" file="spta_system/id1460003.html"/><link parent="topic" id="id1460005" title="Animate modes" file="spta_system/id1460005.html"/></links>